nfcreader/__init__.py
nfcreader/nfcreader.py
nfcreader-0.1.0.dist-info/AUTHORS.rst
nfcreader-0.1.0.dist-info/LICENSE
nfcreader-0.1.0.dist-info/METADATA
nfcreader-0.1.0.dist-info/WHEEL
nfcreader-0.1.0.dist-info/entry_points.txt
nfcreader-0.1.0.dist-info/top_level.txt
nfcreader-0.1.0.dist-info/RECORD
