Metadata-Version: 2.1
Name: nfcreader
Version: 0.1.0
Summary: Python API for NFC reader to run on the Pi Zero.
Home-page: https://github.com/EDWIAN004@myuct.ac.za/nfcreader
Author: Ian Edwards Agoritsa Spirakis
Author-email: ian.edwardsm@gmail.com, agoritsa.spirakis@gmail.com
License: MIT license
Keywords: nfcreader
Platform: UNKNOWN
Classifier: Development Status :: 2 - Pre-Alpha
Classifier: Intended Audience :: Developers
Classifier: License :: OSI Approved :: MIT License
Classifier: Natural Language :: English
Classifier: Programming Language :: Python :: 3
Classifier: Programming Language :: Python :: 3.5
Classifier: Programming Language :: Python :: 3.6
Classifier: Programming Language :: Python :: 3.7
Classifier: Programming Language :: Python :: 3.8
Requires-Python: >=3.5
Requires-Dist: Click (>=7.0)
